{
  "slug": "actusf-le-podcast",
  "title": "Actusf le Podcast !",
  "author": "Jérôme Vincent",
  "type": "podcast",
  "categories": [
    "cinéma",
    "séries"
  ],
  "description": "",
  "image": "https://is1-ssl.mzstatic.com/image/thumb/Podcasts211/v4/7e/f1/ed/7ef1edbc-7770-b0dc-369f-d9ae0c4b044d/mza_16211037198727412896.jpeg/600x600bb.jpg",
  "language": "Livres",
  "platforms": {
    "apple": {
      "url": "https://podcasts.apple.com/fr/podcast/actusf-le-podcast/id1794293583?uo=4",
      "trackId": 1794293583,
      "rating": null,
      "ratingCount": null,
      "episodeCount": 506
    }
  },
  "mediacritic": null,
  "tags": [
    "cinéma",
    "séries"
  ],
  "updatedAt": "2026-05-03"
}