{
  "slug": "archimag-podcast",
  "title": "Archimag Podcast",
  "author": "Archimag",
  "type": "podcast",
  "categories": [
    "tech",
    "numérique"
  ],
  "description": "",
  "image": "https://is1-ssl.mzstatic.com/image/thumb/Podcasts221/v4/50/5e/38/505e38f5-6e78-f55e-8dd7-abe0647645fb/mza_15883258333494072495.jpeg/600x600bb.jpg",
  "language": "Actualités technologiques",
  "platforms": {
    "apple": {
      "url": "https://podcasts.apple.com/fr/podcast/archimag-podcast/id1677818969?uo=4",
      "trackId": 1677818969,
      "rating": null,
      "ratingCount": null,
      "episodeCount": 34
    }
  },
  "mediacritic": null,
  "tags": [
    "tech",
    "numérique"
  ],
  "updatedAt": "2026-05-03"
}