{
  "slug": "avec-grace-cie",
  "title": "Avec Grace & Cie",
  "author": "AvecGrace, votre allié numérique",
  "type": "podcast",
  "categories": [
    "gastronomie",
    "cuisine"
  ],
  "description": "AvecGrace&amp;amp;Cie., c&apos;est quoi ? Un podcast dans lequel on vous présente nos 3M : ▪️ Marketing : la base d&apos;Avec Grace ! Vous découvrirez tous nos conseils et astuces qui touchent tous les volets du marketing ! ▪️Mindset &amp;amp; motivation : parce que vous avez sûrement une idée mais vous avez peur de vous lancer... Nos invité.e.s vous raconteront leurs échecs, leurs histoires, leurs parcours ou encore leurs succès !",
  "image": "https://is1-ssl.mzstatic.com/image/thumb/Podcasts115/v4/3a/ce/47/3ace4702-c2ba-cef4-3bb3-8757e8274c51/mza_570664427182661901.jpg/600x600bb.jpg",
  "language": "Affaires",
  "platforms": {
    "apple": {
      "url": "https://podcasts.apple.com/fr/podcast/avec-grace-cie/id1511118254?uo=4",
      "trackId": 1511118254,
      "rating": null,
      "ratingCount": null,
      "episodeCount": 30
    }
  },
  "mediacritic": null,
  "tags": [
    "gastronomie",
    "cuisine"
  ],
  "updatedAt": "2026-05-03"
}