{
  "slug": "beach-tennis-brasil-podcast",
  "title": "Beach Tennis Brasil Podcast",
  "author": "Beach Tennis Brasil Podcast",
  "type": "podcast",
  "categories": [
    "sport"
  ],
  "description": "",
  "image": "https://is1-ssl.mzstatic.com/image/thumb/Podcasts112/v4/39/04/58/39045805-f9d2-3da8-13a8-9c5c96338eae/mza_8297421223322530974.jpg/600x600bb.jpg",
  "language": "Sports",
  "platforms": {
    "apple": {
      "url": "https://podcasts.apple.com/fr/podcast/beach-tennis-brasil-podcast/id1658048763?uo=4",
      "trackId": 1658048763,
      "rating": null,
      "ratingCount": null,
      "episodeCount": 36
    }
  },
  "mediacritic": null,
  "tags": [
    "sport"
  ],
  "addedAt": "2026-05-17",
  "updatedAt": "2026-05-17"
}