{
  "slug": "ca-commence-aujourd-hui",
  "title": "Ça commence aujourd'hui",
  "author": "France Télévisions",
  "type": "podcast",
  "categories": [
    "culture",
    "société"
  ],
  "description": "&lt;p&gt;Tous les jours, Faustine Bollaert accueille dans Ça commence aujourd'hui des hommes et des femmes qui évoquent des événements marquants de leur existence, pour permettre à d'autres d'avancer dans leur parcours, avec la présence éclairante de nos experts - avocat, psychiatre, psychologue, nutritionniste... : un rendez-vous positif et optimiste.&lt;/p&gt;&lt;p&gt;🎙️ Retrouvez Ça commence aujourd'hui en vidéo sur france·tv : &lt;a href=\"https://www.france.tv/france-2/ca-commence-aujourd-hu",
  "image": "https://is1-ssl.mzstatic.com/image/thumb/Podcasts221/v4/29/59/3f/29593fdc-e675-47fd-7572-fc066afa2e23/mza_14581155191169061898.jpg/600x600bb.jpg",
  "language": "Culture et société",
  "platforms": {
    "apple": {
      "url": "https://podcasts.apple.com/fr/podcast/%C3%A7a-commence-aujourdhui/id1561370616?uo=4",
      "trackId": 1561370616,
      "rating": 4.5,
      "ratingCount": 1390,
      "episodeCount": 198
    }
  },
  "mediacritic": null,
  "tags": [
    "culture",
    "société"
  ],
  "updatedAt": "2026-05-10"
}