{
  "slug": "calivolution",
  "title": "CALIVOLUTION",
  "author": "Matt Breizh",
  "type": "podcast",
  "categories": [
    "sport",
    "running"
  ],
  "description": "",
  "image": "https://is1-ssl.mzstatic.com/image/thumb/Podcasts221/v4/e9/62/80/e962802a-19fd-ad8b-0b45-97ad77e28a4d/mza_8465362402006673004.jpg/600x600bb.jpg",
  "language": "Sports",
  "platforms": {
    "apple": {
      "url": "https://podcasts.apple.com/fr/podcast/calivolution/id1777703088?uo=4",
      "trackId": 1777703088,
      "rating": null,
      "ratingCount": null,
      "episodeCount": 63
    }
  },
  "mediacritic": null,
  "tags": [
    "sport",
    "running"
  ],
  "updatedAt": "2026-05-03"
}