{
  "slug": "calvinball",
  "title": "Calvinball",
  "author": "Zali Falcam",
  "type": "podcast",
  "categories": [
    "gaming",
    "retro"
  ],
  "description": "",
  "image": "https://is1-ssl.mzstatic.com/image/thumb/Podcasts125/v4/76/fe/57/76fe57f5-bc7a-b5b8-d09c-d6bf9efc47c9/mza_3507559837211619096.jpg/600x600bb.jpg",
  "language": "Humour",
  "platforms": {
    "apple": {
      "url": "https://podcasts.apple.com/fr/podcast/calvinball/id1284304233?uo=4",
      "trackId": 1284304233,
      "rating": 5.0,
      "ratingCount": 10,
      "episodeCount": 168
    }
  },
  "mediacritic": null,
  "tags": [
    "gaming",
    "retro"
  ],
  "addedAt": "2026-05-17",
  "updatedAt": "2026-05-19"
}