{
  "slug": "cine-eyes-cast-un-il-libre-sur-le-cinema",
  "title": "Ciné Eyes Cast : Un œil libre sur le cinéma",
  "author": "Vadim Perrod",
  "type": "podcast",
  "categories": [
    "cinema",
    "culture"
  ],
  "description": "",
  "image": "https://is1-ssl.mzstatic.com/image/thumb/Podcasts221/v4/f2/dd/9d/f2dd9d03-98ba-49ae-b6c3-4bd8ac7f412b/mza_534770741063048920.jpg/600x600bb.jpg",
  "language": "Arts visuels",
  "platforms": {
    "apple": {
      "url": "https://podcasts.apple.com/fr/podcast/cin%C3%A9-eyes-cast-un-%C5%93il-libre-sur-le-cin%C3%A9ma/id1835499637?uo=4",
      "trackId": 1835499637,
      "rating": 5.0,
      "ratingCount": 1,
      "episodeCount": 53
    }
  },
  "mediacritic": null,
  "tags": [
    "cinema",
    "culture"
  ],
  "addedAt": "2026-05-17",
  "updatedAt": "2026-05-17"
}