{
  "slug": "comics-outcast",
  "title": "Comics Outcast",
  "author": "Vaisseau Hyper Sensas",
  "type": "podcast",
  "categories": [
    "cinéma",
    "séries"
  ],
  "description": "",
  "image": "https://is1-ssl.mzstatic.com/image/thumb/Podcasts113/v4/12/6e/8f/126e8faa-7ee1-599e-72e5-b1e5987ea93c/mza_1880414713565022589.jpg/600x600bb.jpg",
  "language": "Arts visuels",
  "platforms": {
    "apple": {
      "url": "https://podcasts.apple.com/fr/podcast/comics-outcast/id914285870?uo=4",
      "trackId": 914285870,
      "rating": null,
      "ratingCount": null,
      "episodeCount": 451
    }
  },
  "mediacritic": null,
  "tags": [
    "cinéma",
    "séries"
  ],
  "updatedAt": "2026-05-03"
}