{
  "slug": "cultures-monde",
  "title": "Cultures monde",
  "author": "France Culture",
  "type": "podcast",
  "categories": [
    "culture",
    "société"
  ],
  "description": "",
  "image": "https://is1-ssl.mzstatic.com/image/thumb/Podcasts112/v4/f2/b5/08/f2b5081d-cc48-d54c-0a44-465283ed65de/mza_17487693125235312458.jpg/600x600bb.jpg",
  "language": "Culture et société",
  "platforms": {
    "apple": {
      "url": "https://podcasts.apple.com/fr/podcast/cultures-monde/id417736577?uo=4",
      "trackId": 417736577,
      "rating": 4.3,
      "ratingCount": 637,
      "episodeCount": 112
    }
  },
  "mediacritic": null,
  "tags": [
    "culture",
    "société"
  ],
  "updatedAt": "2026-05-16"
}