{
  "slug": "dans-un-etat-critique",
  "title": "Dans un état... critique !",
  "author": "Lilian Lloyd - Christophe Clauzel - Florian Maubert - Olivier Fournel",
  "type": "podcast",
  "categories": [
    "humour",
    "comedie"
  ],
  "description": "",
  "image": "https://is1-ssl.mzstatic.com/image/thumb/Podcasts211/v4/81/c2/38/81c2389f-9667-be34-88ad-03edfd88f6de/mza_10974539902525163603.jpg/600x600bb.jpg",
  "language": "Cinéma : les critiques",
  "platforms": {
    "apple": {
      "url": "https://podcasts.apple.com/fr/podcast/dans-un-%C3%A9tat-critique/id1789116694?uo=4",
      "trackId": 1789116694,
      "rating": 5.0,
      "ratingCount": 2,
      "episodeCount": 19
    }
  },
  "mediacritic": null,
  "tags": [
    "humour",
    "comedie"
  ],
  "updatedAt": "2026-05-16"
}