{
  "slug": "dans-les-coulisses-du-change",
  "title": "Dans les coulisses du change",
  "author": "WAVESTONE",
  "type": "podcast",
  "categories": [
    "tech",
    "numerique"
  ],
  "description": "",
  "image": "https://is1-ssl.mzstatic.com/image/thumb/Podcasts221/v4/3c/67/0e/3c670ee5-13ae-b2e8-a92f-3f886cc9a13f/mza_4396969662335014042.jpg/600x600bb.jpg",
  "language": "Technologies",
  "platforms": {
    "apple": {
      "url": "https://podcasts.apple.com/fr/podcast/dans-les-coulisses-du-change/id1862165260?uo=4",
      "trackId": 1862165260,
      "rating": 5.0,
      "ratingCount": 2,
      "episodeCount": 4
    }
  },
  "mediacritic": null,
  "tags": [
    "tech",
    "numerique"
  ],
  "addedAt": "2026-05-16",
  "updatedAt": "2026-05-16"
}