{
  "slug": "dans-la-tete-de-nos-enfants",
  "title": "Dans la tête de nos enfants",
  "author": "PLAISIR DAPPRENDRE",
  "type": "podcast",
  "categories": [
    "enfants",
    "éducation"
  ],
  "description": "",
  "image": "https://is1-ssl.mzstatic.com/image/thumb/Podcasts221/v4/2a/98/42/2a98424f-784e-ad24-a911-572daeafb9c8/mza_4307877013047573431.jpeg/600x600bb.jpg",
  "language": "Éducation",
  "platforms": {
    "apple": {
      "url": "https://podcasts.apple.com/fr/podcast/dans-la-t%C3%AAte-de-nos-enfants/id1848043132?uo=4",
      "trackId": 1848043132,
      "rating": null,
      "ratingCount": null,
      "episodeCount": 6
    }
  },
  "mediacritic": null,
  "tags": [
    "enfants",
    "éducation"
  ],
  "updatedAt": "2026-05-03"
}