{
  "slug": "darknet-diaries",
  "title": "Darknet Diaries",
  "author": "Jack Rhysider",
  "type": "podcast",
  "categories": [
    "tech",
    "numerique"
  ],
  "description": "",
  "image": "https://is1-ssl.mzstatic.com/image/thumb/Podcasts122/v4/3a/80/a7/3a80a7db-5620-f77b-9935-016e61cc2fbc/mza_9399859904175514567.jpg/170x170bb.png",
  "language": "fr",
  "platforms": {
    "apple": {
      "url": "https://podcasts.apple.com/fr/podcast/darknet-diaries/id1296350485?uo=2",
      "trackId": 1296350485,
      "rating": 5.0,
      "ratingCount": 109,
      "episodeCount": null
    }
  },
  "mediacritic": null,
  "tags": [
    "tech",
    "numerique"
  ],
  "addedAt": "2026-05-16",
  "updatedAt": "2026-05-16"
}