{
  "slug": "discussions-d-ingenieurs",
  "title": "Discussions d'Ingénieurs",
  "author": "Thomas l'Ingénieur",
  "type": "podcast",
  "categories": [
    "sciences",
    "vulgarisation"
  ],
  "description": "Premier podcast ingénieur de France. Saison 4 sur l&apos;IA (2025). Si vous voulez passer sur ce podcast ▶️ thomas.lingenieur@gmail.com Ma formation pour booster ta carrière avec l&apos;IA 👉 https://youtu.be/gfJXCd6C3WY",
  "image": "https://is1-ssl.mzstatic.com/image/thumb/Podcasts211/v4/46/e6/0e/46e60ede-2824-6e7e-243b-62a6c921d939/mza_6229970261418300467.jpg/600x600bb.jpg",
  "language": "Carrière",
  "platforms": {
    "apple": {
      "url": "https://podcasts.apple.com/fr/podcast/discussions-ding%C3%A9nieurs/id1600219578?uo=4",
      "trackId": 1600219578,
      "rating": 5.0,
      "ratingCount": 21,
      "episodeCount": 68
    }
  },
  "mediacritic": null,
  "tags": [
    "sciences",
    "vulgarisation"
  ],
  "updatedAt": "2026-05-10"
}