{
  "slug": "episode-suivant",
  "title": "Épisode suivant",
  "author": "BFM Business",
  "type": "podcast",
  "categories": [
    "cinéma",
    "séries"
  ],
  "description": "Chaque semaine, Clément Lesaffre et ses invités éclairent l&apos;actualité des plateformes de streaming et vous livrent coups de cœur et coups de gueule sur les séries du moment.",
  "image": "https://is1-ssl.mzstatic.com/image/thumb/Podcasts126/v4/f9/ad/6b/f9ad6b10-074d-5265-e2bb-728e75e21f28/mza_7260132807145594383.jpg/600x600bb.jpg",
  "language": "Technologies",
  "platforms": {
    "apple": {
      "url": "https://podcasts.apple.com/fr/podcast/%C3%A9pisode-suivant/id1559044451?uo=4",
      "trackId": 1559044451,
      "rating": 4.6,
      "ratingCount": 17,
      "episodeCount": 100
    }
  },
  "mediacritic": null,
  "tags": [
    "cinéma",
    "séries"
  ],
  "updatedAt": "2026-05-10"
}