{
  "slug": "erreur-critique",
  "title": "Erreur Critique",
  "author": "Neelam",
  "type": "podcast",
  "categories": [
    "cinema",
    "culture"
  ],
  "description": "",
  "image": "https://is1-ssl.mzstatic.com/image/thumb/Podcasts211/v4/31/e8/85/31e885b9-5473-42a4-16d6-37c0dea0f699/mza_593461406286254511.jpg/600x600bb.jpg",
  "language": "Jeux vidéo",
  "platforms": {
    "apple": {
      "url": "https://podcasts.apple.com/fr/podcast/erreur-critique/id1704386457?uo=4",
      "trackId": 1704386457,
      "rating": 5.0,
      "ratingCount": 2,
      "episodeCount": 42
    }
  },
  "mediacritic": null,
  "tags": [
    "cinema",
    "culture"
  ],
  "addedAt": "2026-05-17",
  "updatedAt": "2026-05-19"
}