{
  "slug": "fin-du-game",
  "title": "Fin du Game",
  "author": "MediaCritic",
  "type": "podcast",
  "categories": [
    "gaming"
  ],
  "description": "Critique et analyse du podcast gaming Fin du Game par MediaCritic. Épisode 9 — podcast jeux vidéo francophone.",
  "image": null,
  "language": "fr",
  "platforms": {},
  "mediacritic": {
    "episodeNumber": 7,
    "episodeSlug": "fin-du-game",
    "analyseUrl": "/episodes/fin-du-game.html"
  },
  "tags": [
    "gaming"
  ],
  "updatedAt": "2026-05-04"
}