{
  "slug": "game-girl",
  "title": "Game Girl",
  "author": "Game Girl",
  "type": "podcast",
  "categories": [
    "gaming"
  ],
  "description": "Hello ! Moi c’est Rashka, créatrice de contenu sur Twitch ! Féministe depuis plusieurs années, j’ai eu envie d’ajouter ma petite pierre à l’édifice de la lutte féministe. J’ai voulu parler du féminisme en l’associant à ma passion de toujours : les jeux vidéos ! C’est ainsi qu’est né le podcast GAME GIRL, dont le nom est un « hommage » à la fameuse GAME BOY que nous avons toutes et tous (quasiment) eu dans notre enfance, et dont le nom est le témoignage d’une époque à laquelle les jeux vidéos éta",
  "image": "https://is1-ssl.mzstatic.com/image/thumb/Podcasts122/v4/b8/53/bd/b853bde5-6f26-7bd4-ee3d-d41f9cdb0746/mza_18316377231620632523.jpg/600x600bb.jpg",
  "language": "Culture et société",
  "platforms": {
    "apple": {
      "url": "https://podcasts.apple.com/fr/podcast/game-girl/id1644169933?uo=4",
      "trackId": 1644169933,
      "rating": null,
      "ratingCount": null,
      "episodeCount": 30
    }
  },
  "mediacritic": null,
  "tags": [
    "gaming"
  ],
  "updatedAt": "2026-05-03"
}