{
  "slug": "generation-voyage-solo",
  "title": "Génération Voyage Solo",
  "author": "L'aventure nomade",
  "type": "podcast",
  "categories": [
    "true crime",
    "societe"
  ],
  "description": "",
  "image": "https://is1-ssl.mzstatic.com/image/thumb/Podcasts211/v4/1f/87/55/1f875502-be79-4462-080a-d7b052f0ca51/mza_18085370460592910587.jpg/170x170bb.png",
  "language": "fr",
  "platforms": {
    "apple": {
      "url": "https://podcasts.apple.com/fr/podcast/g%C3%A9n%C3%A9ration-voyage-solo/id1768681017?uo=2",
      "trackId": 1768681017,
      "rating": 5.0,
      "ratingCount": 75,
      "episodeCount": null
    }
  },
  "mediacritic": null,
  "tags": [
    "true crime",
    "societe"
  ],
  "addedAt": "2026-05-16",
  "updatedAt": "2026-05-16"
}