{
  "slug": "hybrid-podcast",
  "title": "HYBRID Podcast",
  "author": "Rudy Coia",
  "type": "podcast",
  "categories": [
    "sport"
  ],
  "description": "",
  "image": "https://is1-ssl.mzstatic.com/image/thumb/Podcasts211/v4/c3/9d/7e/c39d7ef5-65b5-fbe2-8367-af1c468e2477/mza_11954226472998262134.jpeg/600x600bb.jpg",
  "language": "Sports",
  "platforms": {
    "apple": {
      "url": "https://podcasts.apple.com/fr/podcast/hybrid-podcast/id1547425845?uo=4",
      "trackId": 1547425845,
      "rating": 4.9,
      "ratingCount": 157,
      "episodeCount": 204
    }
  },
  "mediacritic": null,
  "tags": [
    "sport"
  ],
  "addedAt": "2026-05-17",
  "updatedAt": "2026-05-19"
}