{
  "slug": "indiepreneurs",
  "title": "iNDIEPRENEURS",
  "author": "Theo Marechal | THEYO",
  "type": "podcast",
  "categories": [
    "business",
    "entrepreneuriat"
  ],
  "description": "",
  "image": "https://is1-ssl.mzstatic.com/image/thumb/Podcasts116/v4/78/95/b0/7895b0c3-b9e9-a35c-2390-ad70ac6d2e05/mza_3954713203034237947.jpg/600x600bb.jpg",
  "language": "Entreprenariat",
  "platforms": {
    "apple": {
      "url": "https://podcasts.apple.com/fr/podcast/indiepreneurs/id1501892976?uo=4",
      "trackId": 1501892976,
      "rating": null,
      "ratingCount": null,
      "episodeCount": 63
    }
  },
  "mediacritic": null,
  "tags": [
    "business",
    "entrepreneuriat"
  ],
  "updatedAt": "2026-05-03"
}