{
  "slug": "kelly-corrigan-wonders",
  "title": "Kelly Corrigan Wonders",
  "author": "Kelly Corrigan",
  "type": "podcast",
  "categories": [
    "series",
    "cinema"
  ],
  "description": "",
  "image": "https://is1-ssl.mzstatic.com/image/thumb/Podcasts211/v4/a8/f0/ad/a8f0aded-8604-f604-08d7-b546a10bcddc/mza_12212571666396983660.jpg/600x600bb.jpg",
  "language": "Culture et société",
  "platforms": {
    "apple": {
      "url": "https://podcasts.apple.com/fr/podcast/kelly-corrigan-wonders/id1532951390?uo=4",
      "trackId": 1532951390,
      "rating": 5.0,
      "ratingCount": 1,
      "episodeCount": 791
    }
  },
  "mediacritic": null,
  "tags": [
    "series",
    "cinema"
  ],
  "addedAt": "2026-05-17",
  "updatedAt": "2026-05-19"
}