{
  "slug": "l-oreille-mathematique",
  "title": "L'oreille mathématique",
  "author": "Institut Henri Poincaré",
  "type": "podcast",
  "categories": [
    "sciences",
    "vulgarisation"
  ],
  "description": "Les mathématiques sont partout dans notre quotidien. Même dans les objets les plus ordinaires : une robe, un ballon, un jeu vidéo…&nbsp; Au fil des expositions de la Maison Poincaré, plongez dans l’univers passionnant des maths. Accompagnée de mathématicien-nes, de chercheur-euses, de designers, la journaliste Alice Deroide remonte la piste des formes, des calculs qui se dissimulent derrière tous ces objets de notre quotidien. L’oreille mathématique : quand les objets de notre quotidien raconten",
  "image": "https://is1-ssl.mzstatic.com/image/thumb/Podcasts211/v4/63/cc/57/63cc5738-5a1b-657c-b279-9810255f5205/mza_15618962442284880478.jpeg/600x600bb.jpg",
  "language": "Mathématiques",
  "platforms": {
    "apple": {
      "url": "https://podcasts.apple.com/fr/podcast/loreille-math%C3%A9matique/id1506765270?uo=4",
      "trackId": 1506765270,
      "rating": 4.5,
      "ratingCount": 36,
      "episodeCount": 40
    }
  },
  "mediacritic": null,
  "tags": [
    "sciences",
    "vulgarisation"
  ],
  "updatedAt": "2026-05-16"
}