{
  "slug": "la-5e-de-couv",
  "title": "La 5e de Couv'",
  "author": "MediaCritic",
  "type": "podcast",
  "categories": [
    "livres",
    "culture"
  ],
  "description": "Critique et analyse du podcast manga La 5e de Couv&#39; par MediaCritic. Épisode 1 de la saison 1.",
  "image": null,
  "language": "fr",
  "platforms": {},
  "mediacritic": {
    "episodeNumber": 1,
    "episodeSlug": "la-5e-de-couv",
    "analyseUrl": "/episodes/la-5e-de-couv.html"
  },
  "tags": [
    "livres",
    "culture"
  ],
  "updatedAt": "2026-05-04"
}