{
  "slug": "la-chronique-de-marine-leonardi",
  "title": "La chronique de Marine Leonardi",
  "author": "France Inter",
  "type": "podcast",
  "categories": [
    "humour",
    "comedie"
  ],
  "description": "",
  "image": "https://is1-ssl.mzstatic.com/image/thumb/Podcasts221/v4/65/ef/f7/65eff744-6b95-e8ce-9b0a-2112c5502672/mza_1199586226879288564.jpg/170x170bb.png",
  "language": "fr",
  "platforms": {
    "apple": {
      "url": "https://podcasts.apple.com/fr/podcast/la-chronique-de-marine-leonardi/id1768015127?uo=2",
      "trackId": 1768015127,
      "rating": 4.7,
      "ratingCount": 50,
      "episodeCount": null
    }
  },
  "mediacritic": null,
  "tags": [
    "humour",
    "comedie"
  ],
  "addedAt": "2026-05-16",
  "updatedAt": "2026-05-19"
}