{
  "slug": "la-mif",
  "title": "La Mif'",
  "author": "Wecasa France",
  "type": "podcast",
  "categories": [
    "enfants",
    "famille"
  ],
  "description": "",
  "image": "https://is1-ssl.mzstatic.com/image/thumb/Podcasts221/v4/5b/4a/ec/5b4aec6c-e52a-1631-18c1-abfedf610b43/mza_8324214113250444937.jpeg/170x170bb.png",
  "language": "fr",
  "platforms": {
    "apple": {
      "url": "https://podcasts.apple.com/fr/podcast/la-mif/id1848095352?uo=2",
      "trackId": 1848095352,
      "rating": 4.4,
      "ratingCount": 7,
      "episodeCount": null
    }
  },
  "mediacritic": null,
  "tags": [
    "enfants",
    "famille"
  ],
  "addedAt": "2026-05-16",
  "updatedAt": "2026-05-16"
}