{
  "slug": "le-podcast-de-lilou",
  "title": "Le Podcast de Lilou",
  "author": "Lilou Macé",
  "type": "podcast",
  "categories": [
    "sciences",
    "vulgarisation"
  ],
  "description": "",
  "image": "https://is1-ssl.mzstatic.com/image/thumb/Podcasts211/v4/91/c9/7f/91c97f28-1b64-24c1-43e3-b7ce69887da5/mza_15018929497659070566.jpeg/170x170bb.png",
  "language": "fr",
  "platforms": {
    "apple": {
      "url": "https://podcasts.apple.com/fr/podcast/le-podcast-de-lilou/id1873340216?uo=2",
      "trackId": 1873340216,
      "rating": 4.8,
      "ratingCount": 27,
      "episodeCount": null
    }
  },
  "mediacritic": null,
  "tags": [
    "sciences",
    "vulgarisation"
  ],
  "addedAt": "2026-05-16",
  "updatedAt": "2026-05-19"
}