{
  "slug": "le-rendez-vous-tech",
  "title": "Le Rendez-vous Tech",
  "author": "MediaCritic",
  "type": "podcast",
  "categories": [
    "tech",
    "numérique"
  ],
  "description": "Critique et analyse du podcast Le Rendez-vous Tech par MediaCritic. Épisode 7 — meilleur podcast tech francophone.",
  "image": null,
  "language": "fr",
  "platforms": {},
  "mediacritic": {
    "episodeNumber": 10,
    "episodeSlug": "le-rendez-vous-tech",
    "analyseUrl": "/episodes/le-rendez-vous-tech.html"
  },
  "tags": [
    "tech",
    "numérique"
  ],
  "updatedAt": "2026-05-03"
}