{
  "slug": "le-studio",
  "title": "Le Studio",
  "author": "Acast France",
  "type": "podcast",
  "categories": [
    "sciences",
    "vulgarisation"
  ],
  "description": "",
  "image": "https://is1-ssl.mzstatic.com/image/thumb/Podcasts221/v4/7a/25/07/7a250724-6a30-fe34-3eac-ea1168b017fa/mza_9319840312308758149.jpeg/600x600bb.jpg",
  "language": "Actualités",
  "platforms": {
    "apple": {
      "url": "https://podcasts.apple.com/fr/podcast/le-studio/id1591382073?uo=4",
      "trackId": 1591382073,
      "rating": null,
      "ratingCount": null,
      "episodeCount": 32
    }
  },
  "mediacritic": null,
  "tags": [
    "sciences",
    "vulgarisation"
  ],
  "updatedAt": "2026-05-03"
}