{
  "slug": "les-clefs-d-une-vie",
  "title": "Les clefs d'une vie",
  "author": "Sud Radio",
  "type": "podcast",
  "categories": [
    "cinéma",
    "séries"
  ],
  "description": "Jacques Pessis reçoit chaque jour une personnalité pour évoquer les quatre dates qui ont marqué sa vie. Artistes, auteurs et figures emblématiques partagent leurs moments clés dans des échanges riches et intimes. À retrouver du lundi au vendredi de 21h à 22h.",
  "image": "https://is1-ssl.mzstatic.com/image/thumb/Podcasts116/v4/a2/18/ec/a218ec5a-a0e8-88fc-b7d9-3b1a38a881c6/mza_3759486078878613858.jpg/600x600bb.jpg",
  "language": "Culture et société",
  "platforms": {
    "apple": {
      "url": "https://podcasts.apple.com/fr/podcast/les-clefs-dune-vie/id1478245449?uo=4",
      "trackId": 1478245449,
      "rating": null,
      "ratingCount": null,
      "episodeCount": 53
    }
  },
  "mediacritic": null,
  "tags": [
    "cinéma",
    "séries"
  ],
  "updatedAt": "2026-05-03"
}