{
  "slug": "les-voies-de-l-histoire",
  "title": "Les voies de l'Histoire",
  "author": "Le Centre de Recherches en Histoire Internationale et Atlantique (CRHIA)",
  "type": "podcast",
  "categories": [
    "géopolitique",
    "international"
  ],
  "description": "",
  "image": "https://is1-ssl.mzstatic.com/image/thumb/Podcasts221/v4/a7/fc/b1/a7fcb1e8-10cf-d526-4b0a-daecd83efe0d/mza_3427364117528213366.jpg/600x600bb.jpg",
  "language": "Histoire",
  "platforms": {
    "apple": {
      "url": "https://podcasts.apple.com/fr/podcast/les-voies-de-lhistoire/id1660042585?uo=4",
      "trackId": 1660042585,
      "rating": null,
      "ratingCount": null,
      "episodeCount": 60
    }
  },
  "mediacritic": null,
  "tags": [
    "géopolitique",
    "international"
  ],
  "updatedAt": "2026-05-03"
}