{
  "slug": "les-voyages-de-la-foi-la-catechese-immersive",
  "title": "Les voyages de la foi : la catéchèse immersive",
  "author": "Frère Paul Adrien",
  "type": "podcast",
  "categories": [
    "sciences",
    "vulgarisation"
  ],
  "description": "",
  "image": "https://is1-ssl.mzstatic.com/image/thumb/Podcasts211/v4/d9/1d/50/d91d50ad-7aad-7632-b596-0a97cf6407db/mza_7057285975799923160.png/170x170bb.png",
  "language": "fr",
  "platforms": {
    "apple": {
      "url": "https://podcasts.apple.com/fr/podcast/les-voyages-de-la-foi-la-cat%C3%A9ch%C3%A8se-immersive/id1771638328?uo=2",
      "trackId": 1771638328,
      "rating": 4.8,
      "ratingCount": 79,
      "episodeCount": null
    }
  },
  "mediacritic": null,
  "tags": [
    "sciences",
    "vulgarisation"
  ],
  "addedAt": "2026-05-16",
  "updatedAt": "2026-05-19"
}