{
  "slug": "mon-psy-part-en-live",
  "title": "Mon Psy Part En Live",
  "author": "Julien Borloz",
  "type": "podcast",
  "categories": [
    "true crime",
    "societe"
  ],
  "description": "",
  "image": "https://is1-ssl.mzstatic.com/image/thumb/Podcasts115/v4/0b/df/2e/0bdf2ea6-0b20-3086-7bde-4f63a6990ba8/mza_9487519185292605843.jpg/600x600bb.jpg",
  "language": "Santé mentale",
  "platforms": {
    "apple": {
      "url": "https://podcasts.apple.com/fr/podcast/mon-psy-part-en-live/id1588912671?uo=4",
      "trackId": 1588912671,
      "rating": 4.9,
      "ratingCount": 47,
      "episodeCount": 217
    }
  },
  "mediacritic": null,
  "tags": [
    "true crime",
    "societe"
  ],
  "addedAt": "2026-05-16",
  "updatedAt": "2026-05-19"
}