{
  "slug": "monparisport",
  "title": "MonPariSport",
  "author": "Mon Paris FM",
  "type": "podcast",
  "categories": [
    "histoire"
  ],
  "description": "",
  "image": "https://is1-ssl.mzstatic.com/image/thumb/Podcasts122/v4/81/82/69/818269db-d1de-2f72-d8d0-01db23e70514/mza_12701934159023857754.jpg/600x600bb.jpg",
  "language": "Sports",
  "platforms": {
    "apple": {
      "url": "https://podcasts.apple.com/fr/podcast/monparisport/id1735961322?uo=4",
      "trackId": 1735961322,
      "rating": null,
      "ratingCount": null,
      "episodeCount": 162
    }
  },
  "mediacritic": null,
  "tags": [
    "histoire"
  ],
  "updatedAt": "2026-05-03"
}