{
  "slug": "nipedu",
  "title": "Nipédu",
  "author": "Régis Forgione, Fabien Hobart, Jean-Philippe Maitre",
  "type": "podcast",
  "categories": [
    "gaming",
    "retro"
  ],
  "description": "",
  "image": "https://is1-ssl.mzstatic.com/image/thumb/Podcasts126/v4/a6/3c/f8/a63cf8b9-e029-030e-fe41-cd5f21136561/mza_12210454872120333130.jpeg/600x600bb.jpg",
  "language": "Éducation",
  "platforms": {
    "apple": {
      "url": "https://podcasts.apple.com/fr/podcast/nip%C3%A9du/id873600994?uo=4",
      "trackId": 873600994,
      "rating": 5.0,
      "ratingCount": 42,
      "episodeCount": 198
    }
  },
  "mediacritic": null,
  "tags": [
    "gaming",
    "retro"
  ],
  "addedAt": "2026-05-17",
  "updatedAt": "2026-05-17"
}