{
  "slug": "nos-histoires-de-la-television",
  "title": "NOS HISTOIRES DE LA TELEVISION",
  "author": "JeanPat - Patrick Sarréa",
  "type": "podcast",
  "categories": [
    "gaming",
    "rétro"
  ],
  "description": "",
  "image": "https://is1-ssl.mzstatic.com/image/thumb/Podcasts122/v4/e6/86/4c/e6864cde-2d2d-0bfb-7720-4fc51ac20bdd/mza_10680606064382520824.jpg/600x600bb.jpg",
  "language": "Actualité du divertissement",
  "platforms": {
    "apple": {
      "url": "https://podcasts.apple.com/fr/podcast/nos-histoires-de-la-television/id1655690168?uo=4",
      "trackId": 1655690168,
      "rating": null,
      "ratingCount": null,
      "episodeCount": 14
    }
  },
  "mediacritic": null,
  "tags": [
    "gaming",
    "rétro"
  ],
  "updatedAt": "2026-05-03"
}