{
  "slug": "nova-radio-pirate",
  "title": "Nova Radio Pirate",
  "author": "Radio Nova",
  "type": "podcast",
  "categories": [
    "humour",
    "comedie"
  ],
  "description": "",
  "image": "https://is1-ssl.mzstatic.com/image/thumb/Podcasts211/v4/8b/2d/68/8b2d68e9-6533-9231-c6f9-934699f52ca2/mza_10923675835784610197.png/170x170bb.png",
  "language": "fr",
  "platforms": {
    "apple": {
      "url": "https://podcasts.apple.com/fr/podcast/nova-radio-pirate/id1801936458?uo=2",
      "trackId": 1801936458,
      "rating": 4.9,
      "ratingCount": 67,
      "episodeCount": null
    }
  },
  "mediacritic": null,
  "tags": [
    "humour",
    "comedie"
  ],
  "addedAt": "2026-05-16",
  "updatedAt": "2026-05-19"
}