{
  "slug": "odd-lots",
  "title": "Odd Lots",
  "author": "Bloomberg",
  "type": "podcast",
  "categories": [
    "histoire"
  ],
  "description": "",
  "image": "https://is1-ssl.mzstatic.com/image/thumb/Podcasts211/v4/f3/99/6a/f3996a52-e4a4-bf0d-b7d6-e376c4058568/mza_15550359494736224565.jpg/170x170bb.png",
  "language": "fr",
  "platforms": {
    "apple": {
      "url": "https://podcasts.apple.com/fr/podcast/odd-lots/id1056200096?uo=2",
      "trackId": 1056200096,
      "rating": 5.0,
      "ratingCount": 15,
      "episodeCount": null
    }
  },
  "mediacritic": null,
  "tags": [
    "histoire"
  ],
  "addedAt": "2026-05-16",
  "updatedAt": "2026-05-16"
}