{
  "slug": "on-refait-le-mac-orlm",
  "title": "On refait le Mac - ORLM",
  "author": "ORLM.tv by Electric Dreams",
  "type": "podcast",
  "categories": [
    "tech",
    "numérique"
  ],
  "description": "Les podcasts d'ORLM.tv, On refait le Mac et On refait la Tech en version audio ! Retrouvez chaque semaine les débats Tech de référence présentés par Olivier Frigara et la fine équipe d'ORLM et d’ORLT. Hébergé par Acast. Visitez acast.com/privacy pour plus d'informations.",
  "image": "https://is1-ssl.mzstatic.com/image/thumb/Podcasts211/v4/d4/ee/84/d4ee84fe-0751-1287-1ec8-58d0a70782b8/mza_16549799281978892443.jpeg/600x600bb.jpg",
  "language": "Technologies",
  "platforms": {
    "apple": {
      "url": "https://podcasts.apple.com/fr/podcast/on-refait-le-mac-orlm/id1084658910?uo=4",
      "trackId": 1084658910,
      "rating": 4.4,
      "ratingCount": 274,
      "episodeCount": 253
    }
  },
  "mediacritic": null,
  "tags": [
    "tech",
    "numérique"
  ],
  "updatedAt": "2026-05-07"
}