{
  "slug": "podsac",
  "title": "PODSAC",
  "author": "Floydus",
  "type": "podcast",
  "categories": [
    "true crime",
    "societe"
  ],
  "description": "",
  "image": "https://is1-ssl.mzstatic.com/image/thumb/Podcasts211/v4/fc/74/35/fc743599-2e7d-dc69-ba25-e0854a1eba82/mza_9776117929278716752.jpg/600x600bb.jpg",
  "language": "Cinéma : les critiques",
  "platforms": {
    "apple": {
      "url": "https://podcasts.apple.com/fr/podcast/podsac/id723299351?uo=4",
      "trackId": 723299351,
      "rating": 4.6,
      "ratingCount": 37,
      "episodeCount": 97
    }
  },
  "mediacritic": null,
  "tags": [
    "true crime",
    "societe"
  ],
  "addedAt": "2026-05-16",
  "updatedAt": "2026-05-19"
}