{
  "slug": "puissantes",
  "title": "Puissantes",
  "author": "Nejma Ayadi",
  "type": "podcast",
  "categories": [
    "arts",
    "culture"
  ],
  "description": "",
  "image": "https://is1-ssl.mzstatic.com/image/thumb/Podcasts211/v4/f5/9c/fb/f59cfba2-1d11-86b2-635b-f069ba08030a/mza_4693001474356755968.jpeg/170x170bb.png",
  "language": "fr",
  "platforms": {
    "apple": {
      "url": "https://podcasts.apple.com/fr/podcast/puissantes/id1875407061?uo=2",
      "trackId": 1875407061,
      "rating": 4.9,
      "ratingCount": 37,
      "episodeCount": null
    }
  },
  "mediacritic": null,
  "tags": [
    "arts",
    "culture"
  ],
  "addedAt": "2026-05-16",
  "updatedAt": "2026-05-16"
}