{
  "slug": "radical-departures",
  "title": "Radical Departures",
  "author": "OuiStart Media",
  "type": "podcast",
  "categories": [
    "tech",
    "entrepreneuriat"
  ],
  "description": "",
  "image": "https://is1-ssl.mzstatic.com/image/thumb/Podcasts115/v4/02/f2/73/02f2738a-35aa-f2dc-9607-df8049ca762b/mza_17526017477174209498.png/600x600bb.jpg",
  "language": "Technologies",
  "platforms": {
    "apple": {
      "url": "https://podcasts.apple.com/fr/podcast/radical-departures/id1292059754?uo=4",
      "trackId": 1292059754,
      "rating": 5.0,
      "ratingCount": 3,
      "episodeCount": 46
    }
  },
  "mediacritic": null,
  "tags": [
    "tech",
    "entrepreneuriat"
  ],
  "addedAt": "2026-05-16",
  "updatedAt": "2026-05-19"
}