{
  "slug": "sur-la-ligne-nos-archives",
  "title": "Sur La Ligne - Nos archives",
  "author": "KO Studios",
  "type": "podcast",
  "categories": [
    "sport"
  ],
  "description": "",
  "image": "https://is1-ssl.mzstatic.com/image/thumb/Podcasts211/v4/4e/60/6e/4e606ed0-7c52-6fa8-7a9d-7b8c7f1867d7/mza_8512844597313094877.jpeg/600x600bb.jpg",
  "language": "Tennis",
  "platforms": {
    "apple": {
      "url": "https://podcasts.apple.com/fr/podcast/sur-la-ligne-nos-archives/id1539565111?uo=4",
      "trackId": 1539565111,
      "rating": 1.0,
      "ratingCount": 1,
      "episodeCount": 223
    }
  },
  "mediacritic": null,
  "tags": [
    "sport"
  ],
  "addedAt": "2026-05-17",
  "updatedAt": "2026-05-17"
}