{
  "slug": "teasing",
  "title": "Teasing",
  "author": "Les Ondes Mécaniques",
  "type": "podcast",
  "categories": [
    "cinema",
    "culture"
  ],
  "description": "",
  "image": "https://is1-ssl.mzstatic.com/image/thumb/Podcasts125/v4/18/f2/4f/18f24f4f-5c23-5a75-bea6-9ce49dea3e94/mza_17967780319056711259.jpeg/600x600bb.jpg",
  "language": "Arts",
  "platforms": {
    "apple": {
      "url": "https://podcasts.apple.com/fr/podcast/teasing/id1552548770?uo=4",
      "trackId": 1552548770,
      "rating": 5.0,
      "ratingCount": 9,
      "episodeCount": 31
    }
  },
  "mediacritic": null,
  "tags": [
    "cinema",
    "culture"
  ],
  "addedAt": "2026-05-17",
  "updatedAt": "2026-05-19"
}