{
  "slug": "technocurious-france",
  "title": "Technocurious France",
  "author": "Technocurious France",
  "type": "podcast",
  "categories": [
    "gaming",
    "retro"
  ],
  "description": "",
  "image": "https://is1-ssl.mzstatic.com/image/thumb/Podcasts123/v4/a9/55/d2/a955d23e-5c71-09f3-a3a1-8b2f9e1ea60a/mza_8641568715040436499.jpg/600x600bb.jpg",
  "language": "Technologies",
  "platforms": {
    "apple": {
      "url": "https://podcasts.apple.com/fr/podcast/technocurious-france/id1448492112?uo=4",
      "trackId": 1448492112,
      "rating": 5.0,
      "ratingCount": 17,
      "episodeCount": 4
    }
  },
  "mediacritic": null,
  "tags": [
    "gaming",
    "retro"
  ],
  "addedAt": "2026-05-17",
  "updatedAt": "2026-05-17"
}