{
  "slug": "tech-on-me",
  "title": "Tech On Me",
  "author": "Livestream",
  "type": "podcast",
  "categories": [
    "gaming"
  ],
  "description": "Tech On Me, le talk show high-tech animé par PP Garcia ! Chaque épisode : actualités et cultures tech, innovations, invités spéciaux et analyses de passionnés. En LIVE un jeudi sur 2 dès 18 h sur la chaine YouTube PP World et Twitch PP World .&nbsp; Abonnez-vous pour ne rien manquer : nouveautés tech, tendances high-tech, startups et tout ce qui bouge dans le numérique ! Hébergé par Audion. Visitez https://www.audion.fm/fr/privacy-policy pour plus d’informations.",
  "image": "https://is1-ssl.mzstatic.com/image/thumb/Podcasts112/v4/e8/81/cd/e881cd4d-5c29-3ade-0b45-e88a1457c139/mza_12247469208446628849.png/600x600bb.jpg",
  "language": "Actualités technologiques",
  "platforms": {
    "apple": {
      "url": "https://podcasts.apple.com/fr/podcast/tech-on-me/id1734997542?uo=4",
      "trackId": 1734997542,
      "rating": 4.8,
      "ratingCount": 23,
      "episodeCount": 41
    }
  },
  "mediacritic": null,
  "tags": [
    "gaming"
  ],
  "updatedAt": "2026-05-10"
}