{
  "slug": "the-anime-book-club-podcast",
  "title": "The Anime Book Club Podcast",
  "author": "The Anime Book Club Podcast",
  "type": "podcast",
  "categories": [
    "anime",
    "culture"
  ],
  "description": "",
  "image": "https://is1-ssl.mzstatic.com/image/thumb/Podcasts221/v4/ba/c1/ad/bac1ad93-1cb9-6014-094d-231f3be4847b/mza_10101318533981282530.jpg/600x600bb.jpg",
  "language": "Animation et manga",
  "platforms": {
    "apple": {
      "url": "https://podcasts.apple.com/fr/podcast/the-anime-book-club-podcast/id1775312792?uo=4",
      "trackId": 1775312792,
      "rating": null,
      "ratingCount": null,
      "episodeCount": 89
    }
  },
  "mediacritic": null,
  "tags": [
    "anime",
    "culture"
  ],
  "addedAt": "2026-05-17",
  "updatedAt": "2026-05-17"
}