{
  "slug": "the-sonic-podcast",
  "title": "The Sonic Podcast",
  "author": "Podcast Sonic",
  "type": "podcast",
  "categories": [
    "anime",
    "culture"
  ],
  "description": "",
  "image": "https://is1-ssl.mzstatic.com/image/thumb/Podcasts211/v4/53/40/52/534052e4-2a6e-e882-5f7c-e25f95f3991e/mza_2159237247800419465.jpg/600x600bb.jpg",
  "language": "Animation et manga",
  "platforms": {
    "apple": {
      "url": "https://podcasts.apple.com/fr/podcast/the-sonic-podcast/id1542900359?uo=4",
      "trackId": 1542900359,
      "rating": null,
      "ratingCount": null,
      "episodeCount": 1
    }
  },
  "mediacritic": null,
  "tags": [
    "anime",
    "culture"
  ],
  "addedAt": "2026-05-17",
  "updatedAt": "2026-05-17"
}