{
  "slug": "the-b-movie-cast",
  "title": "The B-Movie Cast",
  "author": "Unknown",
  "type": "podcast",
  "categories": [
    "series",
    "cinema"
  ],
  "description": "",
  "image": "https://is1-ssl.mzstatic.com/image/thumb/Podcasts116/v4/7c/5f/99/7c5f99d0-8e1d-5b69-a514-c6654a45b237/mza_14679424481986946788.jpg/600x600bb.jpg",
  "language": "Télévision et cinéma",
  "platforms": {
    "apple": {
      "url": "https://podcasts.apple.com/fr/podcast/the-b-movie-cast/id213753850?uo=4",
      "trackId": 213753850,
      "rating": null,
      "ratingCount": null,
      "episodeCount": 397
    }
  },
  "mediacritic": null,
  "tags": [
    "series",
    "cinema"
  ],
  "addedAt": "2026-05-17",
  "updatedAt": "2026-05-17"
}