{
  "slug": "umento-independants-freelancing-entrepreneuriat",
  "title": "UMento - Indépendants - Freelancing - Entrepreneuriat",
  "author": "Cédric Tempestini",
  "type": "podcast",
  "categories": [
    "rénovation",
    "DIY"
  ],
  "description": "Podcast by Cédric Tempestini",
  "image": "https://is1-ssl.mzstatic.com/image/thumb/Podcasts123/v4/df/1a/ec/df1aec0b-c2d1-ce8d-fe29-821863d32773/mza_7626310961704491147.jpg/600x600bb.jpg",
  "language": "Affaires",
  "platforms": {
    "apple": {
      "url": "https://podcasts.apple.com/fr/podcast/umento-ind%C3%A9pendants-freelancing-entrepreneuriat/id1493516818?uo=4",
      "trackId": 1493516818,
      "rating": 5.0,
      "ratingCount": 2,
      "episodeCount": 4
    }
  },
  "mediacritic": null,
  "tags": [
    "rénovation",
    "DIY"
  ],
  "updatedAt": "2026-05-16"
}