{
  "slug": "uniteed-podcast",
  "title": "Uniteed Podcast",
  "author": "Uniteed international",
  "type": "podcast",
  "categories": [
    "tech",
    "entrepreneuriat"
  ],
  "description": "",
  "image": "https://is1-ssl.mzstatic.com/image/thumb/Podcasts125/v4/87/fb/82/87fb82af-738e-2554-4336-15dc15b81580/mza_3940627978441151737.jpg/600x600bb.jpg",
  "language": "Entreprenariat",
  "platforms": {
    "apple": {
      "url": "https://podcasts.apple.com/fr/podcast/uniteed-podcast/id1514647904?uo=4",
      "trackId": 1514647904,
      "rating": 5.0,
      "ratingCount": 10,
      "episodeCount": 12
    }
  },
  "mediacritic": null,
  "tags": [
    "tech",
    "entrepreneuriat"
  ],
  "addedAt": "2026-05-16",
  "updatedAt": "2026-05-19"
}