{
  "slug": "vers-la-liberte-financiere-papa",
  "title": "Vers la Liberté Financière Papa",
  "author": "Sylvain LIGA (Teddy)",
  "type": "podcast",
  "categories": [
    "rénovation",
    "DIY"
  ],
  "description": "Dans ce Podcast vous embarquez avec moi pour parler de liberté et d'indépendance financière, d'entrepreneuriat, d'immobilier, de revenus passifs, dans des discussions techniques, pratiques ou à dimension philosophique. Ce Podcast est réalisé la plupart du temps lors de mes trajets domicile - travail et ne fait pas obligatoirement l'objet de montage audio.",
  "image": "https://is1-ssl.mzstatic.com/image/thumb/Podcasts211/v4/d2/e7/62/d2e7627b-572a-2ae1-831c-3b4cfa8954a4/mza_9583150025641190023.jpg/600x600bb.jpg",
  "language": "Affaires",
  "platforms": {
    "apple": {
      "url": "https://podcasts.apple.com/fr/podcast/vers-la-libert%C3%A9-financi%C3%A8re-papa/id1412320681?uo=4",
      "trackId": 1412320681,
      "rating": 3.4,
      "ratingCount": 7,
      "episodeCount": 58
    }
  },
  "mediacritic": null,
  "tags": [
    "rénovation",
    "DIY"
  ],
  "updatedAt": "2026-05-19"
}